<Properties StartupConfiguration="{A77DEB61-50BA-3D2B-BA85-CD07C2DB2C66}|">
  <MonoDevelop.Ide.Workbench ActiveDocument="Assets/Beta_player/playerController.cs">
    <Files>
      <File FileName="Assets/Menu/MainMenuController.cs" Line="61" Column="1" IsPinned="True" />
      <File FileName="Assets/Beta_player/Animations.cs" Line="66" Column="35" />
      <File FileName="Assets/sounds/audioMaster.cs" Line="36" Column="11" />
      <File FileName="Assets/Beta_player/playerController.cs" Line="195" Column="4" />
      <File FileName="Assets/Scripts/Mushroom_controller.cs" Line="54" Column="1" />
      <File FileName="Assets/sounds/rocket_audio.cs" Line="54" Column="34" />
      <File FileName="Assets/sounds/rocket_trigger.cs" Line="23" Column="28" />
      <File FileName="Assets/Scripts/GameManager.cs" Line="87" Column="1" />
    </Files>
    <Pads>
      <Pad Id="ProjectPad">
        <State name="__root__">
          <Node name="Demo" expanded="True">
            <Node name="Assets" expanded="True">
              <Node name="animations" expanded="True" />
              <Node name="Beta_player" expanded="True">
                <Node name="playerController.cs" selected="True" />
              </Node>
              <Node name="Menu" expanded="True" />
              <Node name="player" expanded="True" />
              <Node name="Scripts" expanded="True" />
              <Node name="sounds" expanded="True" />
            </Node>
          </Node>
        </State>
      </Pad>
      <Pad Id="MonoDevelop.Debugger.WatchPad">
        <State />
      </Pad>
    </Pads>
  </MonoDevelop.Ide.Workbench>
  <MonoDevelop.Ide.DebuggingService.PinnedWatches />
  <MonoDevelop.Ide.Workspace ActiveConfiguration="Debug" />
  <MonoDevelop.Ide.ItemProperties.Assembly-CSharp PreferredExecutionTarget="a99f590e-2e24-4055-967e-0254bf1c53fe" />
  <MonoDevelop.Ide.DebuggingService.Breakpoints>
    <BreakpointStore />
  </MonoDevelop.Ide.DebuggingService.Breakpoints>
  <MultiItemStartupConfigurations />
</Properties>